aily_server_sdk/__init__.py
aily_server_sdk/app.py
aily_server_sdk/conversation.py
aily_server_sdk/data.py
aily_server_sdk/integration/__init__.py
aily_server_sdk/integration/feishu.py
aily_server_sdk/knowledge.py
aily_server_sdk/llm.py
aily_server_sdk/skill.py
aily_server_sdk-0.1.1.dist-info/LICENSE
aily_server_sdk-0.1.1.dist-info/METADATA
aily_server_sdk-0.1.1.dist-info/WHEEL
aily_server_sdk-0.1.1.dist-info/RECORD
