Metadata-Version: 2.1
Name: aily-server-sdk
Version: 0.1.1
Summary: Aily Server SDK
Author: lijiuyang.5137
Author-email: lijiuyang.5137@bytedance.com
Requires-Python: >=3.8.1,<4.0.0
Classifier: License :: OSI Approved :: Apache Software License
Classifier: Programming Language :: Python :: 3
Classifier: Programming Language :: Python :: 3.9
Classifier: Programming Language :: Python :: 3.10
Classifier: Programming Language :: Python :: 3.11
Requires-Dist: aily-core (>=0.1.0b10,<0.2.0)
Requires-Dist: loguru (>=0.7.2,<0.8.0)
Requires-Dist: openai (>=1.31.0,<2.0.0)
Requires-Dist: pydantic (>=2.7.3,<3.0.0)
